jira_python_utils/__init__.py
jira_python_utils/annotate_readme.py
jira_python_utils/bitbucket_reformat_merge_comment.py
jira_python_utils/console_helper.py
jira_python_utils/constants.py
jira_python_utils/file_utils.py
jira_python_utils/helper.py
jira_python_utils/jira_add_change_control_comment.py
jira_python_utils/jira_add_comment.py
jira_python_utils/jira_add_component.py
jira_python_utils/jira_add_label.py
jira_python_utils/jira_assign_issue.py
jira_python_utils/jira_convert_task_session_script_to_readme.py
jira_python_utils/jira_create_issue.py
jira_python_utils/jira_create_release_software_issues.py
jira_python_utils/jira_epics_to_confluence_tables.py
jira_python_utils/jira_get_issue_details.py
jira_python_utils/jira_initiate_workspace.py
jira_python_utils/jira_link_issues.py
jira_python_utils/jira_remove_watcher.py
jira_python_utils/jira_search_issues.py
jira_python_utils/jira_start_task.py
jira_python_utils/jira_sync_workspace.py
jira_python_utils/jira_to_confluence_weekly_progress_report.py
jira_python_utils/scan_jira_dirs.py
jira_python_utils/search_readme.py
jira_python_utils-0.8.0.data/scripts/make_executables_and_aliases.py
jira_python_utils-0.8.0.dist-info/AUTHORS.rst
jira_python_utils-0.8.0.dist-info/LICENSE
jira_python_utils-0.8.0.dist-info/METADATA
jira_python_utils-0.8.0.dist-info/WHEEL
jira_python_utils-0.8.0.dist-info/entry_points.txt
jira_python_utils-0.8.0.dist-info/top_level.txt
jira_python_utils-0.8.0.dist-info/RECORD
