Metadata-Version: 2.1
Name: jira_python_utils
Version: 0.8.0
Summary: Collection of Python utils for interacting with JIRA
Home-page: https://github.com/jai-python3/jira-python-utils
Author: Jai Python3
Author-email: jai.python3@gmail.com
License: GNU General Public License v3
Keywords: jira_python_utils
Classifier: Development Status :: 2 - Pre-Alpha
Classifier: Intended Audience :: Developers
Classifier: License :: OSI Approved :: GNU General Public License v3 (GPLv3)
Classifier: Natural Language :: English
Classifier: Programming Language :: Python :: 3
Classifier: Programming Language :: Python :: 3.5
Classifier: Programming Language :: Python :: 3.6
Classifier: Programming Language :: Python :: 3.7
Classifier: Programming Language :: Python :: 3.8
Requires-Python: >=3.5
License-File: LICENSE
License-File: AUTHORS.rst
Requires-Dist: Click >=7.0
Requires-Dist: Rich
Requires-Dist: jira
